{"Id":"d29dab3c-856a-425b-b20b-4a4e7793e783","Author":"Default User","CreationTime":"2015-08-03T11:05:35.3737991Z","Permission":1,"Title":"New Template","Header":{"Title":"Client Information","Fields":[{"Name":"head_client","DisplayName":"Client(s)","Value":"Modern Diagnostic Laboratory","Icon":null},{"Name":"head_server","DisplayName":"Server(s)","Value":"DB122","Icon":null},{"Name":"head_proposeddate","DisplayName":"Proposed Date","Value":"2015.08.03","Icon":null},{"Name":"head_starttime","DisplayName":"Start Time","Value":"23:00","Icon":null},{"Name":"head_requestor","DisplayName":"Requestor","Value":"efeofko","Icon":null},{"Name":"head_email","DisplayName":"Email","Value":"eoeofk@tt.com","Icon":null},{"Name":"head_type","DisplayName":"Type","Value":"efkoeofe","Icon":null},{"Name":"head_severity","DisplayName":"Severity","Value":"eofoeo","Icon":null},{"Name":"head_changereason","DisplayName":"Change reason","Value":"eokfeof","Icon":null}]},"ChangeDescription":{"Title":"Change Description","Fields":[{"Name":"txt_summary","DisplayName":"Summary of change","Value":"N/A","Icon":null},{"Name":"txt_packagelocation","DisplayName":"Package location","Value":"N/A","Icon":null},{"Name":"txt_instructions","DisplayName":"Deployment Instructions","Value":"N/A","Icon":null},{"Name":"txt_confirmationprocedure","DisplayName":"Confirmation Procedure","Value":"N/A","Icon":null},{"Name":"txt_rollbackplan","DisplayName":"Roll back plan","Value":"N/A","Icon":null}]},"Monitoring":{"Title":"Monitoring","Fields":[{"Name":"txt_responsibleparties","DisplayName":"Responsible parties","Value":"N/A","Icon":null},{"Name":"txt_standardmonitoring","DisplayName":"Standard monitoring","Value":"N/A","Icon":null},{"Name":"txt_specificmonitoring","DisplayName":"Specific monitoring","Value":"N/A","Icon":null},{"Name":"txt_escalationplan","DisplayName":"escalation plan","Value":"N/A","Icon":null}]}}